README.rst
setup.py
AuthGG/__init__.py
AuthGG/admin.py
AuthGG/client.py
AuthGG/error_handler.py
AuthGG/logging.py
AuthGG.egg-info/PKG-INFO
AuthGG.egg-info/SOURCES.txt
AuthGG.egg-info/dependency_links.txt
AuthGG.egg-info/requires.txt
AuthGG.egg-info/top_level.txt