Metadata-Version: 2.1
Name: AuthGG
Version: 0.9
Summary: Identity made simple for developers.
Home-page: https://github.com/rqzu/AuthGG
Author: razu
Author-email: support@xyris.org
License: MIT
Download-URL: https://github.com/rqzu/AuthGG/archive/main.tar.gz
Keywords: auth,authgg,AuthGG
Platform: UNKNOWN
Classifier: Development Status :: 4 - Beta
Classifier: Intended Audience :: Developers
Classifier: Topic :: Software Development :: Build Tools
Classifier: License :: OSI Approved :: MIT License
Classifier: Programming Language :: Python :: 3.6
